odoo/addons/contract_brand/README.rst
odoo/addons/contract_brand/__init__.py
odoo/addons/contract_brand/__manifest__.py
odoo/addons/contract_brand/i18n/contract_brand.pot
odoo/addons/contract_brand/models/__init__.py
odoo/addons/contract_brand/models/contract.py
odoo/addons/contract_brand/readme/CONTRIBUTORS.rst
odoo/addons/contract_brand/readme/DESCRIPTION.rst
odoo/addons/contract_brand/static/description/icon.png
odoo/addons/contract_brand/static/description/index.html
odoo/addons/contract_brand/tests/__init__.py
odoo/addons/contract_brand/tests/test_contract.py
odoo/addons/contract_brand/views/contract.xml
odoo14_addon_contract_brand-14.0.1.0.1.dist-info/METADATA
odoo14_addon_contract_brand-14.0.1.0.1.dist-info/WHEEL
odoo14_addon_contract_brand-14.0.1.0.1.dist-info/top_level.txt
odoo14_addon_contract_brand-14.0.1.0.1.dist-info/RECORD
