Metadata-Version: 2.1
Name: odoo14-addon-contract-brand
Version: 14.0.1.0.1
Summary: This module allows you to manage branded contracts. It adds a brand field on the contract and propagate the value on the invoices.
Home-page: https://github.com/OCA/brand
Author: ACSONE SA/NV,Odoo Community Association (OCA)
Author-email: support@odoo-community.org
License: AGPL-3
Platform: UNKNOWN
Classifier: Programming Language :: Python
Classifier: Framework :: Odoo
Classifier: Framework :: Odoo :: 14.0
Classifier: License :: OSI Approved :: GNU Affero General Public License v3
Requires-Python: >=3.6
Requires-Dist: odoo14-addon-account-brand
Requires-Dist: odoo14-addon-analytic-brand
Requires-Dist: odoo14-addon-contract
Requires-Dist: odoo (<14.1dev,>=14.0a)
